cashfree_lrs_client/__init__.py
cashfree_lrs_client/api/__init__.py
cashfree_lrs_client/api/default_api.py
cashfree_lrs_client/api/lrs_api.py
cashfree_lrs_client/api_client.py
cashfree_lrs_client/api_response.py
cashfree_lrs_client/apis/__init__.py
cashfree_lrs_client/apis/path_to_api.py
cashfree_lrs_client/apis/paths/__init__.py
cashfree_lrs_client/apis/paths/beneficiaries.py
cashfree_lrs_client/apis/paths/fx_rate_details.py
cashfree_lrs_client/apis/paths/orders.py
cashfree_lrs_client/apis/paths/orders_documents_upload.py
cashfree_lrs_client/apis/paths/orders_order_id_documents_upload.py
cashfree_lrs_client/apis/paths/orders_order_id_process.py
cashfree_lrs_client/apis/paths/remitters.py
cashfree_lrs_client/apis/paths/webhooks.py
cashfree_lrs_client/apis/tag_to_api.py
cashfree_lrs_client/apis/tags/__init__.py
cashfree_lrs_client/apis/tags/lrs_api.py
cashfree_lrs_client/configuration.py
cashfree_lrs_client/docs/CreateBeneficiaryRequest.md
cashfree_lrs_client/docs/CreateOrderRequest.md
cashfree_lrs_client/docs/CreateOrderResponse.md
cashfree_lrs_client/docs/CreateRemitterRequest.md
cashfree_lrs_client/docs/Currency.md
cashfree_lrs_client/docs/Error.md
cashfree_lrs_client/docs/FetchForexRateRequest.md
cashfree_lrs_client/docs/LrsApi.md
cashfree_lrs_client/docs/Purpose.md
cashfree_lrs_client/docs/SetupWebhooksRequest.md
cashfree_lrs_client/docs/SuccessMessage.md
cashfree_lrs_client/exceptions.py
cashfree_lrs_client/model/__init__.py
cashfree_lrs_client/model/amount.py
cashfree_lrs_client/model/amount.pyi
cashfree_lrs_client/model/create_beneficiary_request.py
cashfree_lrs_client/model/create_beneficiary_request.pyi
cashfree_lrs_client/model/create_order_request.py
cashfree_lrs_client/model/create_order_request.pyi
cashfree_lrs_client/model/create_order_response.py
cashfree_lrs_client/model/create_order_response.pyi
cashfree_lrs_client/model/create_remitter_request.py
cashfree_lrs_client/model/create_remitter_request.pyi
cashfree_lrs_client/model/currency.py
cashfree_lrs_client-1.0.17.dist-info/METADATA
cashfree_lrs_client-1.0.17.dist-info/WHEEL
cashfree_lrs_client-1.0.17.dist-info/RECORD
